{
  "pages": [
    {
      "title": "基础组件",
      "list": [
        {
          "name": "Button 按钮",
          "url": "/press/button/button"
        },
        {
          "name": "Cell 单元格",
          "url": "/press/cell/cell"
        },
        {
          "name": "Icon 图标",
          "url": "/press/icon/icon"
        },
        {
          "name": "Popup 弹出层",
          "url": "/press/popup/popup"
        },
        {
          "name": "PopupPlus 弹出层",
          "url": "/press/popup-plus/popup-plus"
        },
        {
          "name": "Toast 轻提示",
          "url": "/press/toast/toast"
        },
        {
          "name": "Transition 动画",
          "url": "/press/transition/transition"
        }
      ]
    },
    {
      "title": "表单组件",
      "list": [
        {
          "name": "Checkbox 复选框",
          "url": "/press/checkbox/checkbox"
        },
        {
          "name": "DatetimePicker 时间选择",
          "url": "/press/datetime-picker/datetime-picker"
        },
        {
          "name": "Picker 选择器",
          "url": "/press/picker/picker"
        },
        {
          "name": "PickerPlus 选择器",
          "url": "/press/picker-plus/picker-plus"
        },
        {
          "name": "Switch 切换",
          "url": "/press/switch/switch"
        }
      ]
    },
    {
      "title": "反馈组件",
      "list": [
        {
          "name": "ActionSheet 动作面板",
          "url": "/press/action-sheet/action-sheet"
        },
        {
          "name": "Dialog 弹出框",
          "url": "/press/dialog/dialog"
        },
        {
          "name": "Loading 加载中",
          "url": "/press/loading/loading"
        },
        {
          "name": "LoadingPlus 加载中",
          "url": "/press/loading-plus/loading-plus"
        },
        {
          "name": "Overlay 遮罩层",
          "url": "/press/overlay/overlay"
        },
        {
          "name": "ShareSheet 分享面板",
          "url": "/press/share-sheet/share-sheet"
        },
        {
          "name": "SwipeCell 滑动单元格",
          "url": "/press/swipe-cell/swipe-cell"
        }
      ]
    },
    {
      "title": "展示组件",
      "list": [
        {
          "name": "Circle 环形进度条",
          "url": "/press/circle/circle"
        },
        {
          "name": "Collapse 折叠面板",
          "url": "/press/collapse/collapse"
        },
        {
          "name": "Divider 分割线",
          "url": "/press/divider/divider"
        },
        {
          "name": "Empty 空状态",
          "url": "/press/empty/empty"
        },
        {
          "name": "NoticeBar 通知栏",
          "url": "/press/notice-bar/notice-bar"
        },
        {
          "name": "Steps 步骤条",
          "url": "/press/steps/steps"
        },
        {
          "name": "Sticky 粘性布局",
          "url": "/press/sticky/sticky"
        },
        {
          "name": "Tag 标签",
          "url": "/press/tag/tag"
        }
      ]
    },
    {
      "title": "导航组件",
      "list": [
        {
          "name": "NavBar 导航栏",
          "url": "/press/nav-bar/nav-bar"
        },
        {
          "name": "Tab 标签页",
          "url": "/press/tab/tab"
        }
      ]
    },
    {
      "title": "业务组件",
      "list": [
        {
          "name": "Area 省市区选择",
          "url": "/press/area/area"
        },
        {
          "name": "MessageList 消息列表",
          "url": "/press/message-list/message-list"
        }
      ]
    }
  ]
}